ocean/__init__.py
ocean/automl/__init__.py
ocean/automl/_auto.py
ocean/automl/_params.py
ocean/automl/_prep.py
ocean/automl/_result.py
ocean/preprocessing/__init__.py
ocean/preprocessing/_flow.py
ocean/preprocessing/_preprocessing.py
ocean/save_load_model/__init__.py
ocean/save_load_model/_load.py
ocean/save_load_model/_save.py
ocean_ml-1.0.5.dist-info/LICENSE.txt
ocean_ml-1.0.5.dist-info/METADATA
ocean_ml-1.0.5.dist-info/WHEEL
ocean_ml-1.0.5.dist-info/top_level.txt
ocean_ml-1.0.5.dist-info/RECORD
