Metadata-Version: 2.1
Name: ocean-ml
Version: 1.0.5
Home-page: https://github.com/AgufSamudra/ocean
Author: Gufranaka Samudra
Author-email: gufranakasamudra348@gmail.com
License: MIT
Keywords: python,ocean,machine,learning,machinelearning,automl
Classifier: Programming Language :: Python :: 3
Classifier: License :: OSI Approved :: MIT License
Classifier: Operating System :: OS Independent
License-File: LICENSE.txt
Requires-Dist: numpy (==1.25.1)
Requires-Dist: scikit-learn (==1.3.0)
Requires-Dist: scipy (==1.11.1)
Requires-Dist: tabulate (==0.9.0)
Requires-Dist: xgboost (==1.7.6)
Requires-Dist: pandas (==2.0.3)
